isotherms.py
pyiast.py
pyiast-1.4.dist-info/DESCRIPTION.rst
pyiast-1.4.dist-info/METADATA
pyiast-1.4.dist-info/RECORD
pyiast-1.4.dist-info/WHEEL
pyiast-1.4.dist-info/metadata.json
pyiast-1.4.dist-info/top_level.txt
