Metadata-Version: 2.0
Name: pyiast
Version: 1.4
Summary: Ideal Adsorbed Solution Theory
Home-page: https://github.com/CorySimon/pyIAST
Author: Cory M. Simon
Author-email: CoryMSimon@gmail.com
License: MIT
Download-URL: https://github.com/CorySimon/pyIAST/tarball/master
Keywords: chemistry isotherm iast
Platform: UNKNOWN
Requires-Dist: matplotlib
Requires-Dist: numpy
Requires-Dist: pandas
Requires-Dist: scipy
